geonate/__init__.py
geonate/classify.py
geonate/common.py
geonate/geonate.py
geonate/plot.py
geonate/post_classify.py
geonate/processor.py
geonate-0.1.6.dist-info/licenses/LICENSE
geonate-0.1.6.dist-info/METADATA
geonate-0.1.6.dist-info/WHEEL
geonate-0.1.6.dist-info/entry_points.txt
geonate-0.1.6.dist-info/top_level.txt
geonate-0.1.6.dist-info/RECORD
