Metadata-Version: 2.4
Name: geonate
Version: 0.1.6
Summary: Python package synthesizes conventional tools and codes for image processing
Author-email: Can Nguyen <ntcan.lres@gmail.com>
License: MIT License
Project-URL: Homepage, https://github.com/canng/geonate
Keywords: geonate
Classifier: Intended Audience :: Developers
Classifier: License :: OSI Approved :: MIT License
Classifier: Natural Language :: English
Classifier: Programming Language :: Python :: 3.8
Classifier: Programming Language :: Python :: 3.9
Classifier: Programming Language :: Python :: 3.10
Classifier: Programming Language :: Python :: 3.11
Classifier: Programming Language :: Python :: 3.12
Requires-Python: >=3.8
License-File: LICENSE
Provides-Extra: all
Requires-Dist: geonate[extra]; extra == "all"
Provides-Extra: extra
Requires-Dist: pandas; extra == "extra"
Dynamic: license-file
